fmp_tcc/__init__.py
fmp_tcc/courtois/__init__.py
fmp_tcc/courtois/fmp_data.py
fmp_tcc/courtois/fmp_url.py
fmp_tcc/courtois/plots.py
fmp_tcc/sapar/__init__.py
fmp_tcc/sapar/fmp_url.py
fmp_tcc/sapar/forex_manipulations.py
fmp_tcc/sapar/get_collection_employees.py
fmp_tcc/sapar/get_collection_fs.py
fmp_tcc/sapar/get_collection_ratios.py
fmp_tcc/sapar/get_collection_stocks.py
fmp_tcc/sapar/get_corr_slope.py
fmp_tcc/sapar/get_daily_forex.py
fmp_tcc/sapar/get_forex_data.py
fmp_tcc/sapar/get_info.py
fmp_tcc/sapar/get_plots_corr_slope.py
fmp_tcc/sapar/get_text_data.py
fmp_tcc/sapar/get_plots/__init__.py
fmp_tcc/sapar/get_plots/get_corr_slope.py
fmp_tcc/sapar/get_plots/get_plots_corr_slope.py
fmp_tcc/sapar/get_plots/plot_with_margin.py
fmp_tcc-0.1.24.dist-info/AUTHORS.rst
fmp_tcc-0.1.24.dist-info/LICENSE
fmp_tcc-0.1.24.dist-info/METADATA
fmp_tcc-0.1.24.dist-info/WHEEL
fmp_tcc-0.1.24.dist-info/top_level.txt
fmp_tcc-0.1.24.dist-info/RECORD
