Metadata-Version: 2.1
Name: fmp-tcc
Version: 0.1.24
Summary: A package for aggregating data from FMP.
Home-page: https://github.com/Bayan2019/fmp_tcc
Author: Alexandre Courtois Auberger, Bayan Saparbayeva, and Vish Patel
Author-email: saparbayevabt@gmail.com
License: MIT license
Keywords: fmp_tcc
Platform: UNKNOWN
Classifier: Development Status :: 2 - Pre-Alpha
Classifier: Intended Audience :: Developers
Classifier: License :: OSI Approved :: MIT License
Classifier: Natural Language :: English
Classifier: Programming Language :: Python :: 3
Classifier: Programming Language :: Python :: 3.6
Classifier: Programming Language :: Python :: 3.7
Classifier: Programming Language :: Python :: 3.8
Requires-Python: >=3.6
License-File: LICENSE
License-File: AUTHORS.rst
